[
  {
    "id": "2042530182033215893",
    "text": "One month later - the contagion spreads. \n\nThat 10-11 mbd crude supply lost impact can't be concentrated in Asia alone.\n\n#oott",
    "createdAt": "2026-04-10T09:08:38+00:00",
    "tweetTime": 1775812118000,
    "username": "JuneGoh_Sparta",
    "displayName": "June Goh",
    "url": "https://x.com/JuneGoh_Sparta/status/2042530182033215893",
    "photoUrl": null,
    "hasPhoto": false,
    "likes": 66,
    "retweets": 5,
    "replies": 2,
    "engagement": 82,
    "isRetweet": false,
    "relevance": 20,
    "rawScore": 20082,
    "score": 20082
  },
  {
    "id": "2042509803352920566",
    "text": "The physical premium for Forties hit record levels. \n\nThis is representing the physical North Sea crude that feeds NWE refineries. \n\nMargins are downright negative.\n\n#oott",
    "createdAt": "2026-04-10T07:47:39+00:00",
    "tweetTime": 1775807259000,
    "username": "JuneGoh_Sparta",
    "displayName": "June Goh",
    "url": "https://x.com/JuneGoh_Sparta/status/2042509803352920566",
    "photoUrl": null,
    "hasPhoto": false,
    "likes": 23,
    "retweets": 2,
    "replies": 0,
    "engagement": 27,
    "isRetweet": false,
    "relevance": 20,
    "rawScore": 20027,
    "score": 20027
  },
  {
    "id": "2042525822876061831",
    "text": "Indian oil refiners have splurged on Russian crude in the last two months and expect to continue buying lots for the rest of the year. In March, India imported 1.98m b/d of Russian oil, the highest since June 2023, according to @Kpler data.\n\nhttps://t.co/9J7bWjDd97",
    "createdAt": "2026-04-10T08:51:19+00:00",
    "tweetTime": 1775811079000,
    "username": "JavierBlas",
    "displayName": "Javier Blas",
    "url": "https://x.com/JavierBlas/status/2042525822876061831",
    "photoUrl": null,
    "hasPhoto": false,
    "likes": 141,
    "retweets": 43,
    "replies": 4,
    "engagement": 239,
    "isRetweet": false,
    "relevance": 20,
    "rawScore": 20239,
    "score": 20239
  },
  {
    "id": "2042513767938797798",
    "text": "Day 3 of the ceasefire: no movement in Hormuz \n\n(But the fragile truce seems to be holding on the ground, air and sea, despite sporadic violations, with not major attacks by either Iran or the US)",
    "createdAt": "2026-04-10T08:03:25+00:00",
    "tweetTime": 1775808205000,
    "username": "JavierBlas",
    "displayName": "Javier Blas",
    "url": "https://x.com/JavierBlas/status/2042513767938797798",
    "photoUrl": null,
    "hasPhoto": false,
    "likes": 228,
    "retweets": 47,
    "replies": 17,
    "engagement": 373,
    "isRetweet": false,
    "relevance": 10,
    "rawScore": 10373,
    "score": 10373
  },
  {
    "id": "2042495625250418733",
    "text": "And now is confirmed: Japan will release oil equivalent to 20 days of consumption from its strategic petroleum reserves in May, Prime Minister Sanae Takaichi said.",
    "createdAt": "2026-04-10T06:51:19+00:00",
    "tweetTime": 1775803879000,
    "username": "JavierBlas",
    "displayName": "Javier Blas",
    "url": "https://x.com/JavierBlas/status/2042495625250418733",
    "photoUrl": null,
    "hasPhoto": false,
    "likes": 153,
    "retweets": 29,
    "replies": 4,
    "engagement": 223,
    "isRetweet": false,
    "relevance": 20,
    "rawScore": 20223,
    "score": 20223
  },
  {
    "id": "2042545236707082571",
    "text": "NORTH SEA FORTIES crude prices closed at a record $147 per barrel on April 9. Forties is one of the principal streams in the Brent complex and prices have doubled since before the war between the United States and Iran broke out. Prices have remained high since the ceasefire reflecting the continued scramble for available barrels in the physical market and intense squeeze on North Sea supply. Forties prices have averaged $139 per barrel so far this month but remain slightly below the previous high of $144 in June 2022 (after Russia’s invasion of Ukraine) and well below the record of $205 in June 2008 after adjusting for inflation:",
    "createdAt": "2026-04-10T10:08:27+00:00",
    "tweetTime": 1775815707000,
    "username": "JKempEnergy",
    "displayName": "John Kemp",
    "url": "https://x.com/JKempEnergy/status/2042545236707082571",
    "photoUrl": "https://pbs.twimg.com/media/HFiUCd4asAAGNPn.jpg",
    "hasPhoto": true,
    "likes": 0,
    "retweets": 0,
    "replies": 0,
    "engagement": 0,
    "isRetweet": false,
    "relevance": 38,
    "rawScore": 38300,
    "score": 38300
  },
  {
    "id": "2042469121628287437",
    "text": "China is releasing SPR, but for domestic consumption. \n\nFor oil analysts, global SPR release flow rate is 3.5 million b/d now.",
    "createdAt": "2026-04-10T05:06:00+00:00",
    "tweetTime": 1775797560000,
    "username": "HFI_Research",
    "displayName": "HFI Research",
    "url": "https://x.com/HFI_Research/status/2042469121628287437",
    "photoUrl": null,
    "hasPhoto": false,
    "likes": 55,
    "retweets": 9,
    "replies": 1,
    "engagement": 76,
    "isRetweet": false,
    "relevance": 10,
    "rawScore": 10076,
    "score": 8565
  },
  {
    "id": "2042468061622718645",
    "text": "Oil demand destruction is the only way to balance the market in the near term.\n\nhttps://t.co/DJavvU6ctj",
    "createdAt": "2026-04-10T05:01:47+00:00",
    "tweetTime": 1775797307000,
    "username": "HFI_Research",
    "displayName": "HFI Research",
    "url": "https://x.com/HFI_Research/status/2042468061622718645",
    "photoUrl": null,
    "hasPhoto": false,
    "likes": 38,
    "retweets": 7,
    "replies": 0,
    "engagement": 52,
    "isRetweet": false,
    "relevance": 10,
    "rawScore": 10052,
    "score": 8544
  },
  {
    "id": "2042544290279162288",
    "text": "Oando plans $750 million drilling campaign, expects funding boost from Iran turmoil\nNigeria's Oando aims to boost output via drilling campaign\nInvestor interest in West African oil rising, CEO Tinubu says\nNo need for petrol imports to Nigeria, CEO adds\n#oott https://t.co/BTyWnNo0Y6",
    "createdAt": "2026-04-10T10:04:42+00:00",
    "tweetTime": 1775815482000,
    "username": "staunovo",
    "displayName": "Giovanni Staunovo🛢",
    "url": "https://x.com/staunovo/status/2042544290279162288",
    "photoUrl": null,
    "hasPhoto": false,
    "likes": 0,
    "retweets": 0,
    "replies": 0,
    "engagement": 0,
    "isRetweet": false,
    "relevance": 20,
    "rawScore": 20000,
    "score": 20000
  },
  {
    "id": "2042535145618526715",
    "text": "Indian refiners have splurged on Russian crude in the last two months and expect to continue buying at current lofty levels for the rest of the year, as the country navigates a Middle East supply crunch and the threat of US sanctions begins to fade.\n#oott https://t.co/iMQcvkVZ8h",
    "createdAt": "2026-04-10T09:28:21+00:00",
    "tweetTime": 1775813301000,
    "username": "staunovo",
    "displayName": "Giovanni Staunovo🛢",
    "url": "https://x.com/staunovo/status/2042535145618526715",
    "photoUrl": null,
    "hasPhoto": false,
    "likes": 3,
    "retweets": 2,
    "replies": 1,
    "engagement": 10,
    "isRetweet": false,
    "relevance": 20,
    "rawScore": 20010,
    "score": 20010
  },
  {
    "id": "2042521175339725302",
    "text": "The #copper market continues to stabilise following last month’s sell-off, which was driven by rising growth concerns amid surging energy prices. While those concerns persist, the fundamental outlook is showing signs of improvement. China remains a key driver, with exchange-monitored stockpiles falling 39% over the past four weeks from a record high, while import premiums have climbed to a ten-month high, signalling robust demand.",
    "createdAt": "2026-04-10T08:32:51+00:00",
    "tweetTime": 1775809971000,
    "username": "Ole_S_Hansen",
    "displayName": "Ole S Hansen",
    "url": "https://x.com/Ole_S_Hansen/status/2042521175339725302",
    "photoUrl": "https://pbs.twimg.com/media/HFh8qPvXsAAC3_T.png",
    "hasPhoto": true,
    "likes": 34,
    "retweets": 5,
    "replies": 1,
    "engagement": 47,
    "isRetweet": false,
    "relevance": 10,
    "rawScore": 10347,
    "score": 10347
  },
  {
    "id": "2042504281480180101",
    "text": "#Agriculture: CBOT #wheat futures dropped to a one-month low, down 4% on the week, pressured by profit-taking and technical selling following the recent decline in energy prices. The move also comes after the USDA raised its forecast for end-season global wheat stocks to 283.1 million tons, up from 277 million previously. After holding a net short position for a record duration, hedge funds flipped to a small net long in the week to 31 March, leaving the market exposed to the recent deterioration in both technical and fundamental conditions.",
    "createdAt": "2026-04-10T07:25:43+00:00",
    "tweetTime": 1775805943000,
    "username": "Ole_S_Hansen",
    "displayName": "Ole S Hansen",
    "url": "https://x.com/Ole_S_Hansen/status/2042504281480180101",
    "photoUrl": "https://pbs.twimg.com/media/HFht78rbQAEGHzw.png",
    "hasPhoto": true,
    "likes": 29,
    "retweets": 4,
    "replies": 1,
    "engagement": 40,
    "isRetweet": false,
    "relevance": 10,
    "rawScore": 10340,
    "score": 10340
  },
  {
    "id": "2042494005712171348",
    "text": "North Sea crude prices for immediate delivery continue to highlight mounting stress in the physical market, as European and Asian refiners scramble to secure cargoes to replace volumes lost during the month-long blockade of the Strait of Hormuz.\n\nDated Brent—a key benchmark for physical North Sea shipments—has moved sharply into focus given the signal it provides on overall market tightness. It rose 7% yesterday to USD 132, while the June Brent futures contract lingered around USD 95, underscoring the growing dislocation between prompt supply and forward pricing.\n\nData from LSEG, cited by the Financial Times, show Forties Blend—another marker for immediate delivery—trading close to USD 147 per barrel on Thursday, further highlighting the acute strain in spot markets.",
    "createdAt": "2026-04-10T06:44:53+00:00",
    "tweetTime": 1775803493000,
    "username": "Ole_S_Hansen",
    "displayName": "Ole S Hansen",
    "url": "https://x.com/Ole_S_Hansen/status/2042494005712171348",
    "photoUrl": "https://pbs.twimg.com/media/HFhjiAXbkAApfQw.png",
    "hasPhoto": true,
    "likes": 115,
    "retweets": 32,
    "replies": 5,
    "engagement": 194,
    "isRetweet": false,
    "relevance": 48,
    "rawScore": 48494,
    "score": 48494
  },
  {
    "id": "2042545059669623228",
    "text": "BREAKING: FORTY MILLION LITERS OF RUSSIAN DIESEL APPEARS TO BE HEADING TO CUBA\n\n#OOTT #Cuba #Tankers",
    "createdAt": "2026-04-10T10:07:45+00:00",
    "tweetTime": 1775815665000,
    "username": "TankerTrackers",
    "displayName": "TankerTrackers.com, Inc.",
    "url": "https://x.com/TankerTrackers/status/2042545059669623228",
    "photoUrl": null,
    "hasPhoto": false,
    "likes": 3,
    "retweets": 1,
    "replies": 0,
    "engagement": 5,
    "isRetweet": false,
    "relevance": 38,
    "rawScore": 38005,
    "score": 38005
  },
  {
    "id": "2042536927455257026",
    "text": "BREAKING: TWO MILLION BARRELS OF IRANIAN CRUDE OIL HAVE REACHED INDIA AS PER SANCTIONS WAIVER\n\n#OOTT #IranWar #Tankers",
    "createdAt": "2026-04-10T09:35:26+00:00",
    "tweetTime": 1775813726000,
    "username": "TankerTrackers",
    "displayName": "TankerTrackers.com, Inc.",
    "url": "https://x.com/TankerTrackers/status/2042536927455257026",
    "photoUrl": null,
    "hasPhoto": false,
    "likes": 134,
    "retweets": 35,
    "replies": 1,
    "engagement": 207,
    "isRetweet": false,
    "relevance": 58,
    "rawScore": 58207,
    "score": 58207
  }
]